{"thetaGrid":{"min":-4,"max":4,"n":201},"tauStdStop":0.55,"maxItems":50,"agreeCutoff":4,"items":[{"id":"E1","trait":"E","text":"I am the life of the party.","a":1.8114131160860105,"b":0.93454864460365061,"reverse":false},{"id":"E2","trait":"E","text":"I don't talk a lot.","a":2.094402648513956,"b":0.080648174411589363,"reverse":true},{"id":"E3","trait":"E","text":"I feel comfortable around people.","a":2.1041428901320081,"b":-0.12828022054987817,"reverse":false},{"id":"E4","trait":"E","text":"I keep in the background.","a":2.1964653747536529,"b":0.6291969161611406,"reverse":true},{"id":"E5","trait":"E","text":"I start conversations.","a":2.6282476612753611,"b":-0.204700509873304,"reverse":false},{"id":"E6","trait":"E","text":"I have little to say.","a":1.9363429138333057,"b":-0.383004679230712,"reverse":true},{"id":"E7","trait":"E","text":"I talk to a lot of different people at parties.","a":2.2422548343632527,"b":0.39959791757860375,"reverse":false},{"id":"E8","trait":"E","text":"I don't like to draw attention to myself.","a":1.3885776267182672,"b":0.97084058299610143,"reverse":true},{"id":"E9","trait":"E","text":"I don't mind being the center of attention.","a":1.6404696742809273,"b":0.19670903731335879,"reverse":false},{"id":"E10","trait":"E","text":"I am quiet around strangers.","a":2.0229771462173667,"b":0.98739445452538,"reverse":true},{"id":"N1","trait":"N","text":"I get stressed out easily.","a":2.0273913471174425,"b":0.053281264949915294,"reverse":false},{"id":"N2","trait":"N","text":"I am relaxed most of the time.","a":1.482081210296688,"b":0.8974411223593125,"reverse":true},{"id":"N3","trait":"N","text":"I worry about things.","a":2.0358480530229843,"b":-0.73951328985310061,"reverse":false},{"id":"N4","trait":"N","text":"I seldom feel blue.","a":1.0233479388266915,"b":0.236167628473029,"reverse":true},{"id":"N5","trait":"N","text":"I am easily disturbed.","a":1.4575724546157325,"b":0.50084567392828361,"reverse":false},{"id":"N6","trait":"N","text":"I get upset easily.","a":2.2720900596806985,"b":0.37288570265756776,"reverse":false},{"id":"N7","trait":"N","text":"I change my mood a lot.","a":2.0648356529027692,"b":0.17843064282562091,"reverse":false},{"id":"N8","trait":"N","text":"I have frequent mood swings.","a":2.2353741492285448,"b":0.54041281763602822,"reverse":false},{"id":"N9","trait":"N","text":"I get irritated easily.","a":1.9887168982453451,"b":0.16645945879653848,"reverse":false},{"id":"N10","trait":"N","text":"I often feel blue.","a":1.8680260025794888,"b":0.58824997611807139,"reverse":false},{"id":"A1","trait":"A","text":"I feel little concern for others.","a":1.3804236628331796,"b":-0.50119289371074027,"reverse":true},{"id":"A2","trait":"A","text":"I am interested in people.","a":1.5421125089986198,"b":-0.787385475892406,"reverse":false},{"id":"A3","trait":"A","text":"I insult people.","a":1.0222007788905094,"b":-0.74168493869954855,"reverse":true},{"id":"A4","trait":"A","text":"I sympathize with others' feelings.","a":2.2891475738173011,"b":-0.86661679146510484,"reverse":false},{"id":"A5","trait":"A","text":"I am not interested in other people's problems.","a":1.8650541647552707,"b":-0.6267030687516072,"reverse":true},{"id":"A6","trait":"A","text":"I have a soft heart.","a":1.4316813961933219,"b":-0.730679716564643,"reverse":false},{"id":"A7","trait":"A","text":"I am not really interested in others.","a":1.918247948758673,"b":-0.60511095320164188,"reverse":true},{"id":"A8","trait":"A","text":"I take time out for others.","a":1.6616771383346998,"b":-0.51627969084450553,"reverse":false},{"id":"A9","trait":"A","text":"I feel others' emotions.","a":1.8988084040339219,"b":-0.83413529926128316,"reverse":false},{"id":"A10","trait":"A","text":"I make people feel at ease.","a":1.2352733119977486,"b":-0.32529397633741192,"reverse":false},{"id":"C1","trait":"C","text":"I am always prepared.","a":1.7238147783391249,"b":0.073004477422101949,"reverse":false},{"id":"C2","trait":"C","text":"I leave my belongings around.","a":1.417930696182897,"b":0.40151866216226939,"reverse":true},{"id":"C3","trait":"C","text":"I pay attention to details.","a":1.2874677384104583,"b":-1.0574112849651436,"reverse":false},{"id":"C4","trait":"C","text":"I make a mess of things.","a":1.6781816195109942,"b":0.003475124298100144,"reverse":true},{"id":"C5","trait":"C","text":"I get chores done right away.","a":1.8338882297254078,"b":0.8634291705916739,"reverse":false},{"id":"C6","trait":"C","text":"I often forget to put things back in their proper place.","a":1.7638277447575164,"b":0.22427986326511262,"reverse":true},{"id":"C7","trait":"C","text":"I like order.","a":1.5267584947794235,"b":-0.41003856332826244,"reverse":false},{"id":"C8","trait":"C","text":"I shirk my duties.","a":1.3804491082960697,"b":-0.026327711408215302,"reverse":true},{"id":"C9","trait":"C","text":"I follow a schedule.","a":1.7134804498687901,"b":0.15707061148514734,"reverse":false},{"id":"C10","trait":"C","text":"I am exacting in my work.","a":1.3818422085955353,"b":-0.29767817525468782,"reverse":false},{"id":"O1","trait":"O","text":"I have a rich vocabulary.","a":1.7610321090600032,"b":-0.32448636396154645,"reverse":false},{"id":"O2","trait":"O","text":"I have difficulty understanding abstract ideas.","a":1.7099515747535783,"b":-0.57630923146228963,"reverse":true},{"id":"O3","trait":"O","text":"I have a vivid imagination.","a":1.4374397855623562,"b":-1.1364571365878293,"reverse":false},{"id":"O4","trait":"O","text":"I am not interested in abstract ideas.","a":1.398395476296969,"b":-0.71186023564798573,"reverse":true},{"id":"O5","trait":"O","text":"I have excellent ideas.","a":1.6320928407215207,"b":-0.62826098901808192,"reverse":false},{"id":"O6","trait":"O","text":"I do not have a good imagination.","a":1.5189758884587388,"b":-1.296350078407601,"reverse":true},{"id":"O7","trait":"O","text":"I am quick to understand things.","a":1.3288173624055575,"b":-1.2121671339212714,"reverse":false},{"id":"O8","trait":"O","text":"I use difficult words.","a":1.7421122225213796,"b":0.2570374821593252,"reverse":false},{"id":"O9","trait":"O","text":"I spend time reflecting on things.","a":0.95989359638644423,"b":-1.5999265158872771,"reverse":false},{"id":"O10","trait":"O","text":"I am full of ideas.","a":1.9288616814280508,"b":-0.75142266614662745,"reverse":false}]}